torchlogix/__init__.py
torchlogix/compiled_model.py
torchlogix/functional.py
torchlogix/packbitstensor.py
torchlogix/layers/__init__.py
torchlogix/layers/conv.py
torchlogix/layers/dense.py
torchlogix/layers/groupsum.py
torchlogix/layers/thresholding.py
torchlogix/models/__init__.py
torchlogix/models/baseline_nn.py
torchlogix/models/conv.py
torchlogix/models/dense.py
torchlogix/models/nn.py
torchlogix-0.1.0.dist-info/licenses/LICENSE
torchlogix-0.1.0.dist-info/METADATA
torchlogix-0.1.0.dist-info/WHEEL
torchlogix-0.1.0.dist-info/top_level.txt
torchlogix-0.1.0.dist-info/RECORD
