Metadata-Version: 2.4
Name: torchlogix
Version: 0.1.0
Summary: Differentiable Logic Gate Networks in PyTorch
Home-page: https://github.com/ligerlac/torchlogix
Author: Lino Gerlach
Author-email: Lino Gerlach <lino.oscar.gerlach@cern.ch>
Maintainer-email: Lino Gerlach <lino.oscar.gerlach@cern.ch>
License: MIT
Project-URL: Homepage, https://github.com/ligerlac/torchlogix
Project-URL: Documentation, https://ligerlac.github.io/torchlogix/
Project-URL: Repository, https://github.com/ligerlac/torchlogix
Project-URL: Bug Tracker, https://github.com/ligerlac/torchlogix/issues
Keywords: deep-learning,pytorch,logic-gates,neural-networks,machine-learning
Classifier: Development Status :: 4 - Beta
Classifier: Intended Audience :: Developers
Classifier: Intended Audience :: Science/Research
Classifier: Programming Language :: Python :: 3
Classifier: Programming Language :: Python :: 3.6
Classifier: Programming Language :: Python :: 3.7
Classifier: Programming Language :: Python :: 3.8
Classifier: Programming Language :: Python :: 3.9
Classifier: Programming Language :: Python :: 3.10
Classifier: Programming Language :: Python :: 3.11
Classifier: License :: OSI Approved :: MIT License
Classifier: Operating System :: OS Independent
Classifier: Topic :: Scientific/Engineering
Classifier: Topic :: Scientific/Engineering :: Mathematics
Classifier: Topic :: Scientific/Engineering :: Artificial Intelligence
Requires-Python: >=3.6
License-File: LICENSE
Requires-Dist: torch>=1.6.0
Requires-Dist: numpy>=1.19.0
Requires-Dist: tqdm>=4.50.0
Requires-Dist: scikit-learn>=0.24.0
Requires-Dist: torchvision>=0.8.0
Requires-Dist: rich>=10.0.0
Provides-Extra: dev
Requires-Dist: flake8>=6.1.0; extra == "dev"
Requires-Dist: black>=23.12.1; extra == "dev"
Requires-Dist: isort>=5.13.2; extra == "dev"
Requires-Dist: pre-commit>=3.6.0; extra == "dev"
Requires-Dist: pytest>=8.0.0; extra == "dev"
Requires-Dist: autopep8>=2.0.4; extra == "dev"
Requires-Dist: sphinx>=4.0.0; extra == "dev"
Requires-Dist: sphinx-rtd-theme>=1.0.0; extra == "dev"
Provides-Extra: geometric
Requires-Dist: torch-geometric>=2.0.0; extra == "geometric"
Dynamic: author
Dynamic: home-page
Dynamic: license-file
Dynamic: requires-python
